{
  "updated": "2026-03-11T15:36:21.519403+00:00",
  "data_range": "2026-02-26 to 2026-03-11",
  "days_analyzed": 14,
  "summary_stats": {
    "days_analyzed": 14,
    "date_range": "2026-02-26 to 2026-03-11",
    "sleep": {
      "avg_score": 79.7,
      "avg_hours": 7.3,
      "avg_deep_hours": 1.2,
      "avg_rem_hours": 1.5,
      "avg_efficiency": 82.5,
      "scores": [
        60,
        82,
        80,
        79,
        86,
        81,
        80,
        82,
        86,
        90,
        71,
        72,
        81,
        86
      ]
    },
    "readiness": {
      "avg_score": 85.1,
      "scores": [
        64,
        87,
        91,
        85,
        91,
        82,
        82,
        84,
        90,
        95,
        81,
        82,
        85,
        93
      ]
    },
    "activity": {
      "avg_score": 87.9,
      "avg_steps": 7560.8,
      "avg_calories": 632.8,
      "scores": [
        null,
        97,
        93,
        85,
        87,
        87,
        88,
        94,
        89,
        87,
        78,
        80,
        88,
        90
      ]
    },
    "heart": {
      "avg_hrv": 72.5,
      "avg_resting_hr": 46.9,
      "hrv_values": [
        null,
        79,
        63,
        52,
        66,
        60,
        84,
        46,
        75,
        70,
        88,
        83,
        93,
        83
      ]
    },
    "recovery": {
      "avg_temp_deviation": -0.2,
      "avg_breath_rate": 15.0
    },
    "workouts_count": 20
  },
  "analysis": {
    "overall_assessment": "Your health metrics show generally strong performance with an average sleep score of 79.7/100 and excellent readiness (85.1/100) and activity scores (87.9/100). However, there's concerning variability in your data, particularly the sharp decline on March 11th with a sleep score dropping to 60/100 and readiness falling to 64/100.",
    "whats_going_well": [
      "Your average HRV of 72.5 ms is excellent and shows good autonomic nervous system function, which is crucial for POTS management",
      "You're maintaining consistent sleep duration averaging 7.3 hours, with good nights like March 7th achieving 8 hours and a strong 86/100 sleep score",
      "Your activity level is impressive with 20 workouts over 14 days and peak performance days like March 10th (13,834 steps, 97/100 activity score)"
    ],
    "areas_to_improve": [
      "Deep sleep is inconsistent and often low (0.6-0.8 hours on March 9th and 5th vs 1.5 hours on March 8th) - prioritize consistent bedtime routine and sleep hygiene",
      "Your HRV shows significant day-to-day variation (52 ms on March 8th vs 84 ms on March 5th) - focus on stress management and recovery practices",
      "Activity levels are highly variable with huge swings between rest days (3,330 steps March 8th) and high activity days (13,871 steps March 7th) - aim for more consistent moderate activity"
    ],
    "pots_specific_insights": "The high variability in your metrics, especially the dramatic drop on March 11th, suggests your autonomic nervous system may be experiencing stress cycles typical of POTS. Your relatively low resting heart rate (46.9 bpm average) combined with good HRV indicates your baseline autonomic function is well-managed when consistent.",
    "focus_for_next_week": "Establish a consistent bedtime routine to improve deep sleep quality and reduce the day-to-day variability in your recovery metrics, aiming for at least 1.0-1.5 hours of deep sleep nightly."
  }
}
