{
  "updated": "2026-05-17T15:48:00.423931+00:00",
  "data_range": "2026-04-21 to 2026-05-04",
  "days_analyzed": 14,
  "summary_stats": {
    "days_analyzed": 14,
    "date_range": "2026-04-21 to 2026-05-04",
    "sleep": {
      "avg_score": 85.4,
      "avg_hours": 7.0,
      "avg_deep_hours": 1.2,
      "avg_rem_hours": 1.5,
      "avg_efficiency": 85.1,
      "scores": [
        null,
        82,
        80,
        88,
        85,
        89,
        81,
        93,
        92,
        82,
        86,
        86,
        85,
        81
      ]
    },
    "readiness": {
      "avg_score": 84.6,
      "scores": [
        null,
        77,
        82,
        87,
        89,
        89,
        85,
        83,
        89,
        72,
        89,
        87,
        88,
        83
      ]
    },
    "activity": {
      "avg_score": 86.1,
      "avg_steps": 6292.3,
      "avg_calories": 526.0,
      "scores": [
        85,
        90,
        91,
        89,
        92,
        84,
        78,
        87,
        92,
        87,
        79,
        84,
        80,
        88
      ]
    },
    "heart": {
      "avg_hrv": 63.6,
      "avg_resting_hr": 47.4,
      "hrv_values": [
        35,
        56,
        72,
        77,
        59,
        69,
        75,
        79,
        62,
        40,
        68,
        65,
        63,
        71
      ]
    },
    "recovery": {
      "avg_temp_deviation": 0.0,
      "avg_breath_rate": 15.2
    },
    "workouts_count": 18
  },
  "analysis": {
    "overall_assessment": "Your autonomic function shows concerning volatility with HRV swinging from 35-77ms over recent days, while resting HR remains well-controlled at 44-49 bpm suggesting POTS stability. The consistently low deep sleep (0.6-1.1h most days) may be limiting immune recovery for Hashimoto's management and vestibular compensation capacity.",
    "whats_going_well": [
      "Resting heart rate remains consistently low at 44-49 bpm across all measured days, indicating good baseline autonomic control and POTS stability",
      "Overall sleep scores are strong at 80-89/100 for 6 of 7 recent days with good 7+ hour durations, supporting recovery needs",
      "Activity levels are appropriately graded at 78-92 points with step counts between 3925-8365, avoiding overexertion that could crash autonomic function"
    ],
    "areas_to_improve": [
      "Deep sleep is critically low at 0.6-1.1 hours most nights (well below 1.5+ hour target), limiting immune system repair needed for Hashimoto's management",
      "HRV volatility is concerning with a dramatic drop from 77ms to 35ms between 5/1 and 5/4, suggesting autonomic instability requiring protocol adjustment",
      "The incomplete data on 5/4 (0.8h sleep, missing readiness score) suggests a significant disruption that needs investigation and recovery focus"
    ],
    "autonomic_assessment": "HRV shows high volatility (35-77ms range) indicating unstable autonomic regulation, though the consistent low resting HR (44-49 bpm) suggests your POTS is reasonably controlled. The sharp HRV drop to 35ms on 5/4 coupled with severely reduced sleep duration signals autonomic stress that requires immediate attention to prevent POTS symptom escalation.",
    "thyroid_immune_signals": "Temperature deviations remain stable at 0.0\u00b0C average, suggesting no acute Hashimoto's flare activity. However, consistently inadequate deep sleep (0.6-1.1h vs needed 1.5+ hours) may be compromising immune system repair and potentially allowing low-grade autoimmune activation.",
    "vestibular_readiness": "The dramatic readiness score drop and HRV crash on 5/4 indicates severely limited capacity for vestibular rehab that day. Most other days show readiness scores of 77-89, suggesting good capacity for gentle vestibular exercises, but avoid intense rehab on days when HRV drops below 50ms.",
    "focus_for_next_week": "Prioritize deep sleep optimization through earlier bedtime, cooler room temperature, and potentially adjusting evening magnesium timing, as inadequate deep sleep is the primary limiting factor for both Hashimoto's immune recovery and autonomic stability."
  }
}
