{
  "updated": "2026-04-28T16:30:45.031883+00:00",
  "data_range": "2026-04-15 to 2026-04-28",
  "days_analyzed": 14,
  "summary_stats": {
    "days_analyzed": 14,
    "date_range": "2026-04-15 to 2026-04-28",
    "sleep": {
      "avg_score": 84.9,
      "avg_hours": 7.5,
      "avg_deep_hours": 1.4,
      "avg_rem_hours": 1.7,
      "avg_efficiency": 86.2,
      "scores": [
        81,
        93,
        92,
        82,
        86,
        86,
        85,
        81,
        87,
        83,
        90,
        87,
        80,
        76
      ]
    },
    "readiness": {
      "avg_score": 84.4,
      "scores": [
        85,
        83,
        89,
        72,
        89,
        87,
        88,
        83,
        81,
        88,
        83,
        87,
        87,
        79
      ]
    },
    "activity": {
      "avg_score": 86.3,
      "avg_steps": 6945.2,
      "avg_calories": 545.2,
      "scores": [
        null,
        87,
        92,
        87,
        79,
        84,
        80,
        88,
        83,
        85,
        87,
        89,
        92,
        89
      ]
    },
    "heart": {
      "avg_hrv": 69.0,
      "avg_resting_hr": 47.1,
      "hrv_values": [
        null,
        79,
        62,
        40,
        68,
        65,
        63,
        71,
        90,
        56,
        92,
        71,
        82,
        58
      ]
    },
    "recovery": {
      "avg_temp_deviation": 0.0,
      "avg_breath_rate": 15.5
    },
    "workouts_count": 19
  },
  "analysis": {
    "overall_assessment": "The data shows strong overall management of all three conditions with excellent sleep scores (84.9 average) and healthy HRV (69.0 ms average), but reveals concerning autonomic instability on 4/25 with HRV dropping to 40 ms and resting HR spiking to 51 bpm. Temperature deviations remain stable at 0.0\u00b0C suggesting well-controlled Hashimoto's inflammation, while consistent high readiness scores indicate good capacity for vestibular rehabilitation.",
    "whats_going_well": [
      "Excellent sleep quality with 92-93/100 scores on 4/26-4/27, paired with strong HRV recovery (62-79 ms) demonstrating effective autonomic regulation",
      "Temperature deviations consistently at 0.0\u00b0C across the period indicate well-controlled thyroid inflammation and minimal Hashimoto's flare activity",
      "Activity levels appropriately graded for POTS management, averaging 6945 steps with 86.3/100 activity scores without triggering autonomic crashes"
    ],
    "areas_to_improve": [
      "Address the autonomic crash pattern seen on 4/25 (HRV 40 ms, RHR 51 bpm, sleep duration only 6.9h) by identifying triggers from the previous day's activities",
      "Increase deep sleep consistency - 4/25 showed only 1.2h deep sleep which may have contributed to poor autonomic recovery; optimize evening magnesium timing",
      "Monitor the incomplete data from 4/28 more closely as missing HRV and activity metrics may mask important autonomic status information"
    ],
    "autonomic_assessment": "HRV shows good baseline function at 69.0 ms average, but the dramatic drop to 40 ms on 4/25 with concurrent RHR spike to 51 bpm indicates significant sympathetic overdrive that day. The quick recovery to HRV 79 ms by 4/27 suggests resilient autonomic function when adequately supported by sleep and activity pacing.",
    "thyroid_immune_signals": "Stable temperature deviations at 0.0\u00b0C and consistent deep sleep averaging 1.4-1.7h suggest minimal immune activation and well-controlled Hashimoto's activity. The brief reduction in deep sleep to 1.2h on 4/25 may have contributed to that day's autonomic instability.",
    "vestibular_readiness": "High readiness scores (72-89 range) indicate good nervous system capacity for vestibular rehabilitation most days. The lower readiness of 72 on 4/25 following poor HRV suggests vestibular rehab should have been scaled back that day to prevent additional nervous system stress.",
    "focus_for_next_week": "Investigate what triggered the 4/25 autonomic crash by reviewing the previous day's activities, stress levels, and supplement timing - consider adjusting evening protocol to ensure consistent 7+ hours sleep duration and prevent similar HRV drops."
  }
}
